devjoni/devjoni.py
devjoni-0.0.1.dist-info/LICENSE
devjoni-0.0.1.dist-info/METADATA
devjoni-0.0.1.dist-info/WHEEL
devjoni-0.0.1.dist-info/top_level.txt
devjoni-0.0.1.dist-info/RECORD
