Metadata-Version: 2.1
Name: devjoni
Version: 0.0.1
Summary: A meta package for DEV Joni
Author-email: DEV Joni <solutions@devjoni.com>
Project-URL: Homepage, https://github.com/devjonix/devjoni-meta
Keywords: devjoni
Classifier: Programming Language :: Python :: 3
Classifier: License :: OSI Approved :: GNU General Public License v3 (GPLv3)
Classifier: Operating System :: OS Independent
Requires-Python: >=3.8
License-File: LICENSE
